mi_libreria/__init__.py
mi_libreria/core.py
mi_libreria_tobuja48-0.1.0.dist-info/METADATA
mi_libreria_tobuja48-0.1.0.dist-info/WHEEL
mi_libreria_tobuja48-0.1.0.dist-info/top_level.txt
mi_libreria_tobuja48-0.1.0.dist-info/RECORD
