Metadata-Version: 2.4
Name: mi-libreria-tobuja48
Version: 0.1.0
Summary: Una librería de ejemplo para PyPI
Home-page: https://github.com/tu-usuario/mi-libreria
Author: Tu Nombre
Author-email: Tu Nombre <tu@email.com>
License: MIT
Project-URL: Homepage, https://github.com/tu-usuario/mi-libreria
Project-URL: Repository, https://github.com/tu-usuario/mi-libreria
Classifier: Development Status :: 3 - Alpha
Classifier: Intended Audience :: Developers
Classifier: License :: OSI Approved :: MIT License
Classifier: Programming Language :: Python :: 3
Classifier: Programming Language :: Python :: 3.8
Classifier: Programming Language :: Python :: 3.9
Classifier: Programming Language :: Python :: 3.10
Classifier: Programming Language :: Python :: 3.11
Classifier: Programming Language :: Python :: 3.12
Requires-Python: >=3.8
Requires-Dist: requests>=2.25.0
Provides-Extra: dev
Requires-Dist: pytest>=6.0; extra == "dev"
Requires-Dist: black; extra == "dev"
Requires-Dist: flake8; extra == "dev"
Dynamic: author
Dynamic: home-page
Dynamic: requires-python
